[
  {
    "SequenceName": "S41",
    "SequenceData": [
      2992,
      3404,
      3750,
      4940,
      5081,
      5189,
      5444,
      5496,
      5664,
      5839,
      6046,
      6082,
      6124,
      6180,
      6222,
      6311,
      6558,
      6592,
      6989,
      7030
    ]
  },
  {
    "SequenceName": "S41",
    "SequenceData": [
      2992,
      3404,
      3750,
      4940,
      5081,
      5189,
      5444,
      5496,
      5664,
      5839,
      6046,
      6082,
      6124,
      6180,
      6222,
      6311,
      6558,
      6592,
      6989,
      7030
    ]
  },
  {
    "SequenceName": "S41",
    "SequenceData": [
      4052,
      5256,
      5418,
      5606,
      5738,
      5819,
      5949,
      5956,
      6034,
      6083,
      6121,
      6142,
      6236,
      6308,
      6351,
      6601,
      6695,
      6835,
      7032,
      7106
    ]
  },
  {
    "SequenceName": "S41",
    "SequenceData": [
      4052,
      5256,
      5418,
      5606,
      5738,
      5819,
      5949,
      5956,
      6034,
      6083,
      6121,
      6142,
      6236,
      6308,
      6351,
      6601,
      6695,
      6835,
      7032,
      7106
    ]
  },
  {
    "SequenceName": "S41",
    "SequenceData": [
      4012,
      4176,
      4414,
      4847,
      4979,
      5279,
      5380,
      5470,
      5506,
      5722,
      5759,
      5801,
      5883,
      5977,
      6025,
      6310,
      6445,
      6467,
      6516,
      7150
    ]
  },
  {
    "SequenceName": "S41",
    "SequenceData": [
      4012,
      4176,
      4414,
      4847,
      4979,
      5279,
      5380,
      5470,
      5506,
      5722,
      5759,
      5801,
      5883,
      5977,
      6025,
      6310,
      6445,
      6467,
      6516,
      7150
    ]
  },
  {
    "SequenceName": "S41",
    "SequenceData": [
      3963,
      4444,
      4472,
      4972,
      4992,
      5015,
      5137,
      5673,
      5715,
      5768,
      5864,
      5912,
      5945,
      5975,
      6034,
      6069,
      6075,
      6752,
      6789,
      6815
    ]
  },
  {
    "SequenceName": "S41",
    "SequenceData": [
      3963,
      4444,
      4472,
      4972,
      4992,
      5015,
      5137,
      5673,
      5715,
      5768,
      5864,
      5912,
      5945,
      5975,
      6034,
      6069,
      6075,
      6752,
      6789,
      6815
    ]
  },
  {
    "SequenceName": "S41",
    "SequenceData": [
      3003,
      4145,
      4832,
      5151,
      5272,
      5505,
      5836,
      5878,
      6083,
      6124,
      6208,
      6330,
      6364,
      6443,
      6492,
      6637,
      6757,
      6859,
      7011,
      7063
    ]
  },
  {
    "SequenceName": "S41",
    "SequenceData": [
      3003,
      4145,
      4832,
      5151,
      5272,
      5505,
      5836,
      5878,
      6083,
      6124,
      6208,
      6330,
      6364,
      6443,
      6492,
      6637,
      6757,
      6859,
      7011,
      7063
    ]
  }
]